setup.py
BackTest/__init__.py
BackTest/performance.py
BackTest_Fantasy.egg-info/PKG-INFO
BackTest_Fantasy.egg-info/SOURCES.txt
BackTest_Fantasy.egg-info/dependency_links.txt
BackTest_Fantasy.egg-info/top_level.txt